[{"label": "R-Wert (2021-12-27)", "value": 0.79, "hint": "Kann nur nachh\u00e4ngig gemessen werden. R-Wert gesamt vom 2021-12-27"}, {"label": "7-Tage-Inzidenz", "value": "311.45", "hint": "Inzidenz mit Stand 2022-01-04"}, {"label": "Neue F\u00e4lle gestern", "value": 61905, "hint": "Neue gemeldete F\u00e4lle gestern, 2022-01-04"}, {"label": "Anteil Omikron (2021-12-30)", "value": "14.97%", "hint": "3-Tagesdurchschnitt des relativen Anteils der Omikron-Variante an den Gesamtinfektionen. Stand: 2021-12-30"}, {"label": "Anteil Delta (2021-12-30)", "value": "85.03%", "hint": "3-Tagesdurchschnitt des relativen Anteils der Delta-Variante an den Gesamtinfektionen. Stand: 2021-12-30"}, {"label": "Nowcast Anteil Omikron", "value": "67.21%", "hint": "Projektion Anteil Omikron heute"}, {"label": "Nowcast Anteil Delta", "value": "32.79%", "hint": "Projektion Anteil Delta heute"}, {"label": "Projektion Omikron 50%", "value": "2021-12-31", "hint": "Projektion f\u00fcr Omikron-Anteil > 50%"}, {"label": "Projektion Omikron 95%", "value": "2022-01-19", "hint": "Projektion f\u00fcr Omikron-Anteil > 95%"}, {"label": "Projektion Omikron Fallzahlen in 14 Tagen", "value": 35604, "hint": "Projektion f\u00fcr Omikron-Fallzahlen in 14 Tagen."}, {"label": "Projektion Delta Fallzahlen in 14 Tagen", "value": 989, "hint": "Projektion f\u00fcr Delta-Fallzahlen in 14 Tagen."}, {"label": "Projektion 7-Tage-Inzidenz in 14 Tagen", "value": "289.33", "hint": ""}, {"label": "Steigende F\u00e4lle ab", "value": "2022-01-05", "hint": "Datum, ab welchem Fallzahlen wieder steigen (Projektion)"}]